venc3/__init__.py
venc3/exceptions.py
venc3/helpers.py
venc3/main.py
venc3/prompt.py
venc3/commands/__init__.py
venc3/commands/export.py
venc3/commands/install.py
venc3/commands/new.py
venc3/commands/print.py
venc3/commands/remote.py
venc3/commands/serv.py
venc3/datastore/__init__.py
venc3/datastore/archives.py
venc3/datastore/configuration.py
venc3/datastore/entries.py
venc3/datastore/entry.py
venc3/datastore/hardcoded_assets.py
venc3/datastore/metadata.py
venc3/datastore/taxonomy.py
venc3/datastore/theme.py
venc3/l10n/__init__.py
venc3/l10n/en.py
venc3/l10n/fr.py
venc3/markup_languages/__init__.py
venc3/markup_languages/asciidoc.py
venc3/markup_languages/markdown.py
venc3/markup_languages/restructuredtext.py
venc3/package_data/oembed_providers.json
venc3/package_data/themes/concrete/config.yaml
venc3/package_data/themes/concrete/assets/style.css
venc3/package_data/themes/concrete/chunks/atomEntry.xml
venc3/package_data/themes/concrete/chunks/atomFooter.xml
venc3/package_data/themes/concrete/chunks/atomHeader.xml
venc3/package_data/themes/concrete/chunks/audio.html
venc3/package_data/themes/concrete/chunks/entry.html
venc3/package_data/themes/concrete/chunks/footer.html
venc3/package_data/themes/concrete/chunks/header.html
venc3/package_data/themes/concrete/chunks/rssEntry.xml
venc3/package_data/themes/concrete/chunks/rssFooter.xml
venc3/package_data/themes/concrete/chunks/rssHeader.xml
venc3/package_data/themes/concrete/chunks/video.html
venc3/package_data/themes_assets/VenC-Infinite-Scroll-1.2.0.js
venc3/package_data/themes_assets/VenC-Scripts-Bootstrap-0.0.0.js
venc3/package_data/themes_assets/VenC-Tree-0.2.0.js
venc3/package_data/themes_assets/concrete-dark.png
venc3/package_data/themes_assets/concrete.png
venc3/package_data/themes_templates/images
venc3/package_data/themes_templates/kroki
venc3/package_data/themes_templates/oEmbed
venc3/package_data/themes_templates/pygmentize
venc3/parallelism/__init__.py
venc3/parallelism/build_entries.py
venc-3.2.7.dist-info/entry_points.txt
venc-3.2.7.dist-info/LICENSE.md
venc-3.2.7.dist-info/WHEEL
venc-3.2.7.dist-info/METADATA
venc-3.2.7.dist-info/RECORD
