Metadata-Version: 2.1
Name: VenC
Version: 3.2.7
Summary: A static blog generator.
Author-email: Denis Salem <denissalem@tuxfamily.org>
Classifier: Environment :: Console
Classifier: Development Status :: 5 - Production/Stable
Classifier: Programming Language :: Python :: 3
Requires-Dist: pyyaml
Requires-Dist: unidecode
Project-URL: documentation, https://venc.software
Project-URL: source, https://framagit.org/denissalem/VenC
